radicale_timerange_indexed_storage/__init__.py
radicale_timerange_indexed_storage/tests/__init__.py
radicale_timerange_indexed_storage/tests/test_radicale_timerange_indexed_storage.py
radicale_timerange_indexed_storage-1.5.2.dist-info/DESCRIPTION.rst
radicale_timerange_indexed_storage-1.5.2.dist-info/METADATA
radicale_timerange_indexed_storage-1.5.2.dist-info/RECORD
radicale_timerange_indexed_storage-1.5.2.dist-info/WHEEL
radicale_timerange_indexed_storage-1.5.2.dist-info/metadata.json
radicale_timerange_indexed_storage-1.5.2.dist-info/top_level.txt
