Metadata-Version: 2.0
Name: radicale-timerange-indexed-storage
Version: 1.5.2
Summary: A time range indexed radicale storage
Home-page: UNKNOWN
Author: Florian Mounier - Kozea
Author-email: florian.mounier@kozea.fr
License: BSD
Platform: Any
Classifier: Development Status :: 5 - Production/Stable
Classifier: Intended Audience :: Developers
Classifier: License :: OSI Approved :: BSD License
Classifier: Operating System :: OS Independent
Classifier: Programming Language :: Python :: 2
Classifier: Programming Language :: Python :: 3
Requires-Dist: radicale
Provides-Extra: test
Requires-Dist: pytest; extra == 'test'
Requires-Dist: pytest-cov; extra == 'test'
Requires-Dist: pytest-flake8; extra == 'test'
Requires-Dist: pytest-isort; extra == 'test'
Requires-Dist: pytest-runner; extra == 'test'
